README.md
setup.py
email_domain_verification/__init__.py
email_domain_verification/emails.py
email_domain_verification/interfaces.py
email_domain_verification/utils.py
email_domain_verification/validators.py
email_domain_verification/verification.py
email_domain_verification.egg-info/PKG-INFO
email_domain_verification.egg-info/SOURCES.txt
email_domain_verification.egg-info/dependency_links.txt
email_domain_verification.egg-info/requires.txt
email_domain_verification.egg-info/top_level.txt