Metadata-Version: 2.1
Name: email-domain-verification
Version: 1.1.0
Summary: Email Validator
Home-page: https://github.com/Khodnevis-Research-Lab/email-domain-verification
Author: Mahdi Niknejad, Khodnevisai.com
Author-email: mmahdiniknejad@gmail.com
Project-URL: Documentation, https://github.com/Khodnevis-Research-Lab/email-domain-verification
Project-URL: Source, https://github.com/Khodnevis-Research-Lab/email-domain-verification
Project-URL: Tracker, https://github.com/Khodnevis-Research-Lab/email-domain-verification/issues
Classifier: Development Status :: 5 - Production/Stable
Classifier: Environment :: Web Environment
Classifier: Intended Audience :: Developers
Classifier: License :: OSI Approved :: GNU Library or Lesser General Public License (LGPL)
Classifier: Operating System :: OS Independent
Classifier: Programming Language :: Python
Classifier: Programming Language :: Python :: 3
Classifier: Programming Language :: Python :: 3.7
Classifier: Programming Language :: Python :: 3.8
Classifier: Programming Language :: Python :: 3.9
Classifier: Programming Language :: Python :: 3.10
Classifier: Programming Language :: Python :: 3.11
Classifier: Topic :: Software Development
Requires-Python: >=3.7
